pytbai/__init__.py
pytbai/core.py
pytbai/definitions.py
pytbai/templates/__init__.py
pytbai/templates/XML/__init__.py
pytbai/templates/XML/tbai_structure.xml
pytbai/templates/XSD/Anula_ticketBaiV1-2-1.xsd
pytbai/templates/XSD/__init__.py
pytbai/templates/XSD/ticketBaiV1-2-1.xsd
pytbai/utils/__init__.py
pytbai/utils/crypto.py
pytbai/utils/xml.py
pytbai-1.6.3.dist-info/LICENSE
pytbai-1.6.3.dist-info/METADATA
pytbai-1.6.3.dist-info/WHEEL
pytbai-1.6.3.dist-info/top_level.txt
pytbai-1.6.3.dist-info/RECORD
