Metadata-Version: 2.1
Name: pytbai
Version: 1.6.3
Summary: pytbai allows to create, manage and send TicketBai invoices to the Basque tax authorities
Home-page: https://github.com/codesyntax/pytbai
Author: Urtzi Odriozola
Author-email: uodriozola@codesyntax.com
License: Copyright 2023 CodeSyntax
Classifier: Intended Audience :: Developers
Classifier: License :: OSI Approved :: MIT License
Classifier: Programming Language :: Python
Classifier: Programming Language :: Python :: 3
Classifier: Programming Language :: Python :: 3.9
Classifier: Programming Language :: Python :: 3.10
Classifier: Programming Language :: Python :: 3.11
License-File: LICENSE
Requires-Dist: requests
Requires-Dist: pyOpenSSL <=23.2.0
Requires-Dist: cryptography <=41.0.7
Requires-Dist: signxml <=3.2.1
